Metadata-Version: 2.1
Name: TextToSpeechPy
Version: 0.0.3
Summary: Text To Speech with defferent voice.
Author-email: ranjitmaity95@gmail.com
